<tool_message>
	<semantic_event id='1' name='PROBLEM_START'>
		<description>The starts the problem: Homework1,part3:Wizard</description>
		<problem_start_operation title='Homework1,part3:Wizard' />
	</semantic_event>
	<event_descriptor>
		<action></action>
		<selection></selection>
		<input></input>
	</event_descriptor>
</tool_message>


<tool_message>
	<semantic_event id='179' name='WORKBENCH_ADD_FLASK'>
		<description>A 250mL Erlenmeyer Flask (ID4) is added to the workbench. The contained solution is: Solution C (0E0g of H2O, 1E-7M of H+, 1E-7M of OH-, 1E0M of C; V=100 mL, T=298.15K).
		</description>
		<workbench_add_flask_from_stockroom_operation workbench='Workbench 1' realm='default' solution='/stockroom/Solution C' time_ms='1138319514687' />
	</semantic_event>
	<event_descriptor>
		<action></action>
		<selection></selection>
		<input></input>
	</event_descriptor>
</tool_message>

<tool_message>
	<semantic_event id='202' name='WORKBENCH_ADD_FLASK'>
		<description>A 250mL Erlenmeyer Flask (ID7) is added to the workbench. The contained solution is: Solution A (0E0g of H2O, 1E-7M of H+, 1E-7M of OH-, 1E0M of A; V=100 mL, T=298.15K).</description>
		<workbench_add_flask_from_stockroom_operation workbench='Workbench 1' realm='default' solution='/stockroom/Solution A' time_ms='1138319865199' />
	</semantic_event>
	<event_descriptor>
		<action></action>
		<selection></selection>
		<input></input>
	</event_descriptor>
</tool_message>

<tool_message>
	<semantic_event id='216' name='SOLUTION_MIX'>
		<description>100 mL from 250mL Erlenmeyer Flask (ID7) that contains Solution A (0E0g of H2O, 1E-7M of H+, 1E-7M of OH-, 1E0M of A; V=100 mL, T=298.15K) are poured into 600mL Beaker (ID9) that contains 600mL Beaker (; V=0 mL, T=298.15K). The resulting solution is 600mL Beaker (0E0g of H2O, 1E-7M of H+, 1E-7M of OH-, 1E0M of A; V=100 mL, T=298.15K).</description>
		<solution_mix_operation source_id='7' source_temperature='298.15' recipient_id='9' recipient_temperature='298.15' volume='0.1' time_ms='1138319900724' /></semantic_event>
	<event_descriptor><action></action><selection></selection><input></input></event_descriptor>
</tool_message>